src/__init__.py
src/main.py
src/train.py
src/data_processing/__init__.py
src/data_processing/data_balancing.py
src/data_processing/feature_engineering.py
src/data_processing/feature_selection.py
src/data_processing/preprocess.py
src/evaluation/__init__.py
src/evaluation/metrics.py
src/explainability/__init__.py
src/explainability/explanation_generator.py
src/explainability/integrated_gradients.py
src/explainability/subgraph_matcher.py
src/knowledge_graph/__init__.py
src/knowledge_graph/cot_generator.py
src/knowledge_graph/kg_constructor.py
src/knowledge_graph/kg_updater.py
src/models/__init__.py
src/models/gnn_model.py
src/models/graph_sage_model.py
src/models/graph_sage_prep.py
src/models/hybrid_model.py
src/visualization/__init__.py
src/visualization/kg_visualizer.py
src/visualization/visualizer.py
cotkg_network_intrusion_detection-0.1.1.dist-info/LICENSE
cotkg_network_intrusion_detection-0.1.1.dist-info/METADATA
cotkg_network_intrusion_detection-0.1.1.dist-info/WHEEL
cotkg_network_intrusion_detection-0.1.1.dist-info/top_level.txt
cotkg_network_intrusion_detection-0.1.1.dist-info/RECORD
