Metadata-Version: 2.1
Name: cotkg-network-intrusion-detection
Version: 0.1.1
Summary: A network intrusion detection system using Chain of Thought, knowledge graphs and GraphSAGE
Home-page: https://github.com/chenxingqiang/cotkg-network-intrusion-detection
Author: Chen Xingqiang
Author-email: chen.xingqiang@iechor.com
Classifier: Development Status :: 3 - Alpha
Classifier: Intended Audience :: Developers
Classifier: License :: OSI Approved :: MIT License
Classifier: Operating System :: OS Independent
Classifier: Programming Language :: Python :: 3
Classifier: Programming Language :: Python :: 3.7
Classifier: Programming Language :: Python :: 3.8
Classifier: Programming Language :: Python :: 3.9
Requires-Python: >=3.7
License-File: LICENSE
Requires-Dist: numpy
Requires-Dist: pandas
Requires-Dist: scikit-learn
Requires-Dist: torch
Requires-Dist: torch-geometric
Requires-Dist: networkx
Requires-Dist: py2neo
Requires-Dist: matplotlib
Requires-Dist: seaborn
Requires-Dist: tsfresh
Requires-Dist: shap
Requires-Dist: transformers
Requires-Dist: openai
Requires-Dist: tqdm
